gsheets_import/__init__.py
gsheets_import/admin.py
gsheets_import/forms.py
gsheets_import/google_sheet_format.py
gsheets_import/static/gsheets_import/css/file_and_google.css
gsheets_import/static/gsheets_import/css/sticky.css
gsheets_import/static/gsheets_import/js/import_gs.js
gsheets_import/static/gsheets_import/js/sticky.js
gsheets_import/static/gsheets_import/js/sticky_helpers.js
gsheets_import/templates/admin/gsheets_import/import.html
gsheets_import/templates/forms/widgets/file_and_google.html
django_gsheets_import-0.0.4.dist-info/LICENSE
django_gsheets_import-0.0.4.dist-info/METADATA
django_gsheets_import-0.0.4.dist-info/WHEEL
django_gsheets_import-0.0.4.dist-info/top_level.txt
django_gsheets_import-0.0.4.dist-info/RECORD
