Metadata-Version: 2.1
Name: django-gsheets-import
Version: 0.0.4
Summary: A Django app to import tabular data from Google Sheets
Home-page: https://github.com/kenkuhhaut/django-gsheets-import
Author: Alexander Helmboldt
Author-email: alexander.helmboldt@embl.de
License: BSD-2-Clause
Project-URL: Bug Tracker, https://github.com/kenkuhhaut/django-gsheets-import/issues
Project-URL: Documentation, https://django-gsheets-import.readthedocs.io/en/latest/
Project-URL: Source Code, https://github.com/kenkuhhaut/django-gsheets-import
Keywords: django,django-admin,google sheets,google drive,data import
Platform: UNKNOWN
Classifier: Development Status :: 3 - Alpha
Classifier: Topic :: Software Development
Classifier: Intended Audience :: Developers
Classifier: License :: OSI Approved :: BSD License
Classifier: Environment :: Web Environment
Classifier: Framework :: Django
Classifier: Framework :: Django :: 3.2
Classifier: Programming Language :: Python
Classifier: Programming Language :: Python :: 3
Classifier: Programming Language :: Python :: 3 :: Only
Classifier: Programming Language :: Python :: 3.8
Requires-Python: >=3.8
License-File: LICENSE
Requires-Dist: Django (>=3.2)
Requires-Dist: django-import-export (>=2.5.0)
Requires-Dist: google-api-python-client (>=2.1.0)
